<?xml version="1.0" ?>
<multilanguage>
  <default>
    <language>en</language>
  </default>
  <list>
    <string>
      <key>$DESCRIPTION</key>
      <language>
        <ko>DLST는 Unity 프로젝트 내 중복 라이브러리를 쉽게 검색하고 삭제할 수 있는 서비스입니다.</ko>
        <en>Duplicate Library Search Tool, or DLST,  searches and removes duplicate libraries.</en>
      </language>
    </string>
    <string>
      <key>$IMAGE_DLST</key>
      <language>
        <ko>DLST</ko>
        <en>DLST</en>
      </language>
    </string>
    <string>
      <key>$IMAGE_IGNORE_STRING</key>
      <language>
        <ko>라이브러리 이름에서 무시할 문자열 설정</ko>
        <en>Ignore particular character strings in a library name</en>
      </language>
    </string>
    <string>
      <key>$IMAGE_IGNORE_LIBRARY</key>
      <language>
        <ko>검색 제외 라이브러리 설정</ko>
        <en>Library names to be excluded from search</en>
      </language>
    </string>
  </list>
</multilanguage>
